{"_handleNewStatus": [Function anonymous],
 "_nativeOnError": [Function anonymous],
"_nativeOnFullscreenUpdate": [Function anonymous],

"_nativeOnLoad": [Function anonymous],
"_nativeOnLoadStart": [Function anonymous],
"_nativeOnPlaybackStatusUpdate": [Function anonymous],
"_nativeOnReadyForDisplay": [Function anonymous],
"_nativeRef": {"current": {"_reactInternalInstance": [Object],
"_reactInternals": [FiberNode],
"context": [Object],
"nativeTag": 103,
"props": [Object],
"refs": [Object],
"state": null,
"updater": [Object]}},
"_onPlaybackStatusUpdate": null,
"_performOperationAndHandleStatusAsync": [Function anonymous],
"_reactInternalInstance": {},
"_reactInternals": {"_debugHookTypes": null,
"_debugNeedsRemount": false,
"_debugOwner": {"_debugHookTypes": [Array],
"_debugNeedsRemount": false,
"_debugOwner": [FiberNode],
"_debugSource": undefined,
"actualDuration": 2.9807811975479126,
"actualStartTime": 723123183.301543,
"alternate": [FiberNode],
"child": [FiberNode],
"childLanes": 0,
"deletions": null,
"dependencies": null,
"elementType": [Function Player],
"flags": 8388609,
"index": 0,
"key": null,
"lanes": 1,
"memoizedProps": [Object],
"memoizedState": [Object],
"mode": 2,
"pendingProps": [Object],
"ref": null,
"return": [FiberNode],
"selfBaseDuration": 0.3109370470046997,
"sibling": null,
"stateNode": null,
"subtreeFlags": 8407045,
"tag": 0,
"treeBaseDuration": 2.882344126701355,
"type": [Function Player],
"updateQueue": [Object]},
"_debugSource": undefined,
"actualDuration": 0.8395302295684814,
"actualStartTime": 723123184.513054,
"alternate": {"_debugHookTypes": null,
"_debugNeedsRemount": false,
"_debugOwner": [FiberNode],
"_debugSource": undefined,
"actualDuration": 0.9409914016723633,
"actualStartTime": 723123677.217949,
"alternate": [Circular],
"child": [FiberNode],
"childLanes": 0,
"deletions": null,
"dependencies": null,
"elementType": [Function Video],
"flags": 1,
"index": 0,
"key": null,
"lanes": 0,
"memoizedProps": [Object],
"memoizedState": [Object],
"mode": 2,
"pendingProps": [Object],
"ref": [Object],
"return": [FiberNode],
"selfBaseDuration": 0.4452090263366699,
"sibling": [FiberNode],
"stateNode": [Circular],
"subtreeFlags": 5,
"tag": 1,
"treeBaseDuration": 0.8969281911849976,
"type": [Function Video],
"updateQueue": [Object]},
"child": {"_debugHookTypes": null,
"_debugNeedsRemount": false,
"_debugOwner": [Circular],
"_debugSource": null,
"actualDuration": 0.43499910831451416,
"actualStartTime": 723123184.919095,
"alternate": [FiberNode],
"child": [FiberNode],
"childLanes": 0,
"deletions": null,
"dependencies": null,
"elementType": [Object],
"flags": 1,
"index": 0,
"key": null,
"lanes": 0,
"memoizedProps": [Object],
"memoizedState": null,
"mode": 2,
"pendingProps": [Object],
"ref": null,
"return": [Circular],
"selfBaseDuration": 0.17354202270507812,
"sibling": null,
"stateNode": null,
"subtreeFlags": 5,
"tag": 11,
"treeBaseDuration": 0.4032810926437378,
"type": [Object],
"updateQueue": null},
"childLanes": 0,
"deletions": null,
"dependencies": null,
"elementType": [Function Video],
"flags": 1,
"index": 0,
"key": null,
"lanes": 0,
"memoizedProps": {"isLooping": true,
"onPlaybackStatusUpdate": [Function onPlaybackStatusUpdate],
"resizeMode": "contain",
"shouldPlay": true,
"source": [Object],
"style": [Array],
"useNativeControls": false},
"memoizedState": {"showPoster": false},
"mode": 2,
"pendingProps": {"isLooping": true,
"onPlaybackStatusUpdate": [Function onPlaybackStatusUpdate],
"resizeMode": "contain",
"shouldPlay": true,
"source": [Object],
"style": [Array],
"useNativeControls": false},
"ref": {"current": [Circular]},
"return": {"_debugHookTypes": null,
"_debugNeedsRemount": false,
"_debugOwner": [FiberNode],
"_debugSource": undefined,
"actualDuration": 1.8204160928726196,
"actualStartTime": 723123184.465554,
"alternate": [FiberNode],
"child": [Circular],
"childLanes": 0,
"deletions": null,
"dependencies": null,
"elementType": "RCTView",
"flags": 4,
"index": 0,
"key": null,
"lanes": 0,
"memoizedProps": [Object],
"memoizedState": null,
"mode": 2,
"pendingProps": [Object],
"ref": null,
"return": [FiberNode],
"selfBaseDuration": 0.04552102088928223,
"sibling": null,
"stateNode": [ReactNativeFiberHostComponent],
"subtreeFlags": 8390661,
"tag": 5,
"treeBaseDuration": 1.755729079246521,
"type": "RCTView",
"updateQueue": null},
"selfBaseDuration": 0.4013020992279053,
"sibling": {"_debugHookTypes": null,
"_debugNeedsRemount": false,
"_debugOwner": [FiberNode],
"_debugSource": undefined,
"actualDuration": 0.929999828338623,
"actualStartTime": 723123185.378574,
"alternate": [FiberNode],
"child": [FiberNode],
"childLanes": 0,
"deletions": null,
"dependencies": null,
"elementType": [Object],
"flags": 1,
"index": 1,
"key": null,
"lanes": 0,
"memoizedProps": [Object],
"memoizedState": null,
"mode": 2,
"pendingProps": [Object],
"ref": null,
"return": [FiberNode],
"selfBaseDuration": 0.12994801998138428,
"sibling": null,
"stateNode": null,
"subtreeFlags": 8390661,
"tag": 11,
"treeBaseDuration": 0.9056248664855957,
"type": [Object],
"updateQueue": null},
"stateNode": [Circular],
"subtreeFlags": 5,
"tag": 1,
"treeBaseDuration": 0.8045831918716431,
"type": [Function Video],
"updateQueue": {"baseState": [Object],
"effects": null,
"firstBaseUpdate": null,
"lastBaseUpdate": null,
"shared": [Object]}},
"state": {"showPoster": false},
"unloadAsync": [Function anonymous],
"updater": {"enqueueForceUpdate": [Function enqueueForceUpdate],
"enqueueReplaceState": [Function enqueueReplaceState],
"enqueueSetState": [Function enqueueSetState],
"isMounted": [Function isMounted]}}  





LOG  {"androidImplementation": "SimpleExoPlayer",
"audioPan": 0,
"didJustFinish": false,
"durationMillis": 1434880,
"isBuffering": false,
"isLoaded": true,
"isLooping": true,
"isMuted": false,
"isPlaying": true,
"playableDurationMillis": 1218560,
"positionMillis": 1168047,
"progressUpdateIntervalMillis": 500,
"rate": 1,
"shouldCorrectPitch": false,
"shouldPlay": true,
"uri": "/hls-playback/73d95f50d84c53a7d28c3ce0ec2a2bee49fbae21e2a76e6a376f900fbaeec42ad7dd15e4f99d107a460b490b5f930c09a2fb9a352b632a7becbf3977f8452fad003adea08bbce1eb1075ccbfae943f1ad7b7ab1b0faa131362ef5a6b4ec36c8c22cbec1eb345660de2a46925c0d3411cf53234a750d4e5a9a098020f83536fbaf73ddefff03a853cc83ed7c2c76fb478/master.m3u8",
"volume": 1}




{"current": 
{
    "_captureRef": [Function anonymous], 
    "_getItem": [Function anonymous], 
    "_getItemCount": [Function anonymous], 
    "_keyExtractor": [Function anonymous], 
    "_listRef": 
    {
        "__getFrameMetricsApprox": [Function anonymous], 
        "_averageCellLength": 0, 
        "_captureScrollRef": [Function anonymous], 
        "_cellRefs": [Object], 
        "_convertParentScrollMetrics": [Function anonymous], 
        "_createViewToken": [Function anonymous], 
        "_defaultRenderScrollComponent": [Function anonymous], 
        "_fillRateHelper": [FillRateHelper], 
        "_footerLength": 0, 
        "_frames": [Object], 
        "_getFrameMetrics": [Function anonymous], 
        "_getNonViewportRenderRegions": [Function anonymous], 
        "_getOffsetApprox": [Function anonymous], 
        "_getOutermostParentListRef": [Function anonymous], 
        "_getScrollMetrics": [Function anonymous], 
        "_getSpacerKey": [Function anonymous], 
        "_hasInteracted": false, 
        "_hasMore": false, 
        "_hasTriggeredInitialScrollToIndex": false, 
        "_hasWarned": [Object], 
        "_headerLength": 0, 
        "_hiPriInProgress": false, 
        "_highestMeasuredFrameIndex": 0, 
        "_inAsyncStateUpdate": false, 
        "_indicesToKeys": [Map], 
        "_lastFocusedCellKey": null, 
        "_nestedChildLists": [ChildListCollection], 
        "_offsetFromParentVirtualizedList": 0, 
        "_onCellLayout": [Function anonymous], 
        "_onCellUnmount": [Function anonymous], 
        "_onContentSizeChange": [Function anonymous], 
        "_onLayout": [Function anonymous], 
        "_onLayoutEmpty": [Function anonymous], 
        "_onLayoutFooter": [Function anonymous], 
        "_onLayoutHeader": [Function anonymous], 
        "_onMomentumScrollBegin": [Function anonymous], 
        "_onMomentumScrollEnd": [Function anonymous], 
        "_onScroll": [Function anonymous], 
        "_onScrollBeginDrag": [Function anonymous], 
        "_onScrollEndDrag": [Function anonymous], 
        "_onUpdateSeparators": [Function anonymous], 
        "_prevParentOffset": 0, 
        "_reactInternalInstance": [Object], 
        "_reactInternals": [FiberNode], 
        "_registerAsNestedChild": [Function anonymous], 
        "_scrollMetrics": [Object], 
        "_scrollRef": [ReactNativeFiberHostComponent], 
        "_sentEndForContentLength": 0, 
        "_sentStartForContentLength": 0, 
        "_totalCellLength": 0, 
        "_totalCellsMeasured": 0, 
        "_unregisterAsNestedChild": [Function anonymous], 
        "_updateCellsToRender": [Function anonymous], 
        "_updateCellsToRenderBatcher": [Batchinator], 
        "_viewabilityTuples": [Array], 
        "context": null, 
        "props": [Object], 
        "refs": [Object], 
        "updater": [Object]
    },
    "_memoizedRenderer": [Function memoized], 
    "_reactInternalInstance": {}, 
    "_reactInternals": {"_debugHookTypes": null, 
    "_debugNeedsRemount": false, 
    "_debugOwner": [FiberNode], 
    "_debugSource": undefined, 
    "actualDuration": 31.167920112609863, 
    "actualStartTime": 981328127.081064, 
    "alternate": null, 
    "child": [FiberNode], 
    "childLanes": 0, 
    "deletions": null, 
    "dependencies": null, 
    "elementType": [Function FlatList], 
    "flags": 1049089, 
    "index": 1, 
    "key": null, 
    "lanes": 0, 
    "memoizedProps": [Object], 
    "memoizedState": null, 
    "mode": 2, 
    "pendingProps": [Object], 
    "ref": [Circular], 
    "return": [FiberNode], 
    "selfBaseDuration": 0.2151559591293335, 
    "sibling": null, 
    "stateNode": [Circular], 
    "subtreeFlags": 9439749, 
    "tag": 1, 
    "treeBaseDuration": 21.074114561080933, 
    "type": [Function FlatList], 
    "updateQueue": [Object]}, 
    "_renderer": [Function anonymous], 
    "_virtualizedListPairs": [], 
    "context": {}, 
    "props": {"contentContainerStyle": [Object], 
    "data": [Array], 
    "numColumns": 5, 
    "renderItem": [Function renderItem]}, 
    "refs": {}, 
    "state": null, 
    "updater": 
    {
        "enqueueForceUpdate": [Function enqueueForceUpdate], 
        "enqueueReplaceState": [Function enqueueReplaceState], 
        "enqueueSetState": [Function enqueueSetState], 
        "isMounted": [Function isMounted]
    }
}
}